mafunction/__init__.py
mafunction/maithe.py
mafunction-0.0.1.dist-info/METADATA
mafunction-0.0.1.dist-info/WHEEL
mafunction-0.0.1.dist-info/license.txt
mafunction-0.0.1.dist-info/top_level.txt
mafunction-0.0.1.dist-info/RECORD
