Metadata-Version: 2.1
Name: mafunction
Version: 0.0.1
Summary: pythonlibrary
Author: anisa
Keywords: python
Classifier: Development Status :: 1 - Planning
Classifier: Intended Audience :: Developers
Classifier: Programming Language :: Python :: 3
Classifier: Operating System :: Unix
Classifier: Operating System :: MacOS :: MacOS X
Classifier: Operating System :: Microsoft :: Windows
License-File: license.txt
